aklearn/__init__.py
algokit_learn-0.0.1.dist-info/METADATA
algokit_learn-0.0.1.dist-info/WHEEL
algokit_learn-0.0.1.dist-info/top_level.txt
algokit_learn-0.0.1.dist-info/RECORD
