Metadata-Version: 2.1
Name: algokit-learn
Version: 0.0.1
Summary: AKLearn: A user-friendly machine learning library implemented from scratch in Python.
Home-page: https://github.com/iajaykarthick/algokit-learn
Author: Ajay Karthick
Classifier: Programming Language :: Python :: 3
Classifier: License :: OSI Approved :: MIT License
Classifier: Operating System :: OS Independent
Requires-Python: >=3.6
